{
  "schema_version": "1.0",
  "generated_at": "2026-03-26T03:24:47+00:00",
  "atom_id": "ageoa.scipy.interpolate_v2.rbfinterpolatorfit@ageoa/scipy/interpolate_v2/atoms.py:42",
  "atom_name": "ageoa.scipy.interpolate_v2.rbfinterpolatorfit",
  "atom_key": "scipy/interpolate_v2:rbfinterpolatorfit",
  "mapping_found": true,
  "upstream_mapping": {
    "repo": null,
    "module": "scipy.interpolate",
    "function": "RBFInterpolator",
    "language": "python",
    "notes": "Standard library; no third_party repo"
  },
  "wrapper_signature": {
    "parameter_names": [
      "y",
      "d",
      "neighbors",
      "smoothing",
      "kernel",
      "epsilon",
      "degree"
    ],
    "required_parameter_names": [
      "y",
      "d"
    ],
    "return_annotation": "object"
  },
  "upstream_signature": {
    "parameter_names": [
      "y",
      "d",
      "neighbors",
      "smoothing",
      "kernel",
      "epsilon",
      "degree"
    ],
    "required_parameter_names": [
      "y",
      "d"
    ],
    "parameters": [
      {
        "name": "y",
        "required": true,
        "kind": "positional_or_keyword",
        "annotation": null
      },
      {
        "name": "d",
        "required": true,
        "kind": "positional_or_keyword",
        "annotation": null
      },
      {
        "name": "neighbors",
        "required": false,
        "kind": "positional_or_keyword",
        "annotation": null
      },
      {
        "name": "smoothing",
        "required": false,
        "kind": "positional_or_keyword",
        "annotation": null
      },
      {
        "name": "kernel",
        "required": false,
        "kind": "positional_or_keyword",
        "annotation": null
      },
      {
        "name": "epsilon",
        "required": false,
        "kind": "positional_or_keyword",
        "annotation": null
      },
      {
        "name": "degree",
        "required": false,
        "kind": "positional_or_keyword",
        "annotation": null
      }
    ],
    "return_annotation": null
  },
  "upstream_signature_source": "inspect",
  "upstream_signature_ref": "scipy.interpolate",
  "findings": [
    "FIDELITY_WEAK_TYPES"
  ],
  "notes": [],
  "fidelity_status": "partial",
  "missing_required_parameters": [],
  "invented_parameters": [],
  "runtime_probe": {
    "status": "not_applicable",
    "findings": [
      "RUNTIME_PROBE_SKIPPED"
    ],
    "notes": [
      "Atom is outside the conservative safe probe allowlist."
    ],
    "source_refs": [
      {
        "path": "ageoa/scipy/interpolate_v2/atoms.py",
        "line": 42
      }
    ],
    "schema_version": "1.0",
    "generated_at": "2026-03-26T03:24:52+00:00",
    "atom_id": "ageoa.scipy.interpolate_v2.rbfinterpolatorfit@ageoa/scipy/interpolate_v2/atoms.py:42",
    "atom_name": "ageoa.scipy.interpolate_v2.rbfinterpolatorfit",
    "probe_status": "skipped",
    "positive_probe": {
      "status": "not_applicable"
    },
    "negative_probe": {
      "status": "not_applicable"
    },
    "parity_used": false,
    "skip_reason": "unsupported_scope",
    "exception_type": null,
    "exception_message": null
  },
  "return_fidelity": {
    "schema_version": "1.0",
    "generated_at": "2026-03-26T03:25:01+00:00",
    "atom_id": "ageoa.scipy.interpolate_v2.rbfinterpolatorfit@ageoa/scipy/interpolate_v2/atoms.py:42",
    "status": "pass",
    "findings": [],
    "notes": [],
    "source_refs": [
      {
        "path": "ageoa/scipy/interpolate_v2/atoms.py",
        "line": 42
      }
    ],
    "returned_names": [
      "RBFInterpolator",
      "d",
      "degree",
      "epsilon",
      "kernel",
      "neighbors",
      "smoothing",
      "y"
    ],
    "call_assignment_targets": []
  },
  "state_fidelity": {
    "schema_version": "1.0",
    "generated_at": "2026-03-26T03:25:11+00:00",
    "atom_id": "ageoa.scipy.interpolate_v2.rbfinterpolatorfit@ageoa/scipy/interpolate_v2/atoms.py:42",
    "status": "not_applicable",
    "findings": [],
    "notes": [
      "Atom is not marked stateful in the manifest."
    ],
    "source_refs": [
      {
        "path": "ageoa/scipy/interpolate_v2/atoms.py",
        "line": 42
      }
    ],
    "state_fields": [],
    "updated_fields": []
  },
  "generated_nouns": {
    "schema_version": "1.0",
    "generated_at": "2026-03-26T03:25:14+00:00",
    "atom_id": "ageoa.scipy.interpolate_v2.rbfinterpolatorfit@ageoa/scipy/interpolate_v2/atoms.py:42",
    "status": "not_applicable",
    "findings": [],
    "notes": [
      "No output dict keys or model_copy(update=...) keys were found."
    ],
    "source_refs": [
      {
        "path": "ageoa/scipy/interpolate_v2/atoms.py",
        "line": 42
      },
      {
        "path": "/Users/conrad/personal/ageo-atoms/data/audit/allowlists/generated_nouns.json"
      }
    ],
    "candidate_nouns": [],
    "undocumented_nouns": []
  }
}
